[
  {
    "url": "https://photos.peterlyons.com/2013/2013-03-03-017MS279KG5CRD3DMJZ3XHX2Z2.2048.jpg",
    "caption": "Turkey cake - basic patty"
  },
  {
    "url": "https://photos.peterlyons.com/2013/2013-03-03-017MS28028TZSZ75YG7YKKZM55.2048.jpg",
    "caption": "Turkey cake - basic patty"
  },
  {
    "url": "https://photos.peterlyons.com/2013/2013-03-03-017MS28JM0WHFREM1M1D1B15QP.2048.jpg",
    "caption": "Turkey cake - stuffing at the ready"
  },
  {
    "url": "https://photos.peterlyons.com/2013/2013-03-03-017MS2CEMRDZT9R507MCKJWSSQ.2048.jpg",
    "caption": "Turkey cake - mashed potato layer"
  },
  {
    "url": "https://photos.peterlyons.com/2013/2013-03-03-017MS2JWPGA27PRF6J7ZQCTB2G.2048.jpg",
    "caption": "Turkey cake"
  },
  {
    "url": "https://photos.peterlyons.com/2013/2013-03-03-017MS2KAC059RHMWH7TAW1M46E.2048.jpg",
    "caption": "Turkey cake - stuffing layer"
  },
  {
    "url": "https://photos.peterlyons.com/2013/2013-03-03-017MS2PFY0G2RCZ6E0ZP4RZV79.2048.jpg",
    "caption": "Turkey cake - cranberry layer"
  },
  {
    "url": "https://photos.peterlyons.com/2013/2013-03-03-017MS2SXA0JHKRK7ZH9YQMMK5M.2048.jpg",
    "caption": "Turkey cake - sweet potato layer"
  },
  {
    "url": "https://photos.peterlyons.com/2013/2013-03-03-017MS37WJGAQNANEPPFW1FCNAA.2048.jpg",
    "caption": "Turkey cake - decorative marshmellow top layer"
  },
  {
    "url": "https://photos.peterlyons.com/2013/2013-03-03-017MS38M0GJD69B39PGWRA5BV6.2048.jpg",
    "caption": "Turkey cake - decorative marshmellow top layer"
  },
  {
    "url": "https://photos.peterlyons.com/2013/2013-03-03-017MS3ES90AVRN9HW04ES1WP16.2048.jpg",
    "caption": "Turkey cake - decorative marshmellow top layer"
  },
  {
    "url": "https://photos.peterlyons.com/2013/2013-03-03-017MS3K5X01W9MY3KMMQEKHZ9B.2048.jpg",
    "caption": "Turkey cake - in to the oven"
  },
  {
    "url": "https://photos.peterlyons.com/2013/2013-03-03-017MS4AYMRJBA3X9436DN3Y56F.2048.jpg",
    "caption": "Turkey cake - perfectly browned"
  },
  {
    "url": "https://photos.peterlyons.com/2013/2013-03-03-017MS4EJVGA6PR4SV61CEYQ9DY.2048.jpg",
    "caption": "Turkey cake - cranberry cake decoration"
  },
  {
    "url": "https://photos.peterlyons.com/2013/2013-03-03-017MS4K4BRR1WB7YBD55KPA6CA.2048.jpg",
    "caption": "Turkey cake - served!"
  }
]
