[
  {
    "url": "https://photos.peterlyons.com/2009/2009-04-08-01423E8N30Q7Z9QDQ3PR0GYHR1.2048.jpg",
    "caption": "Pickup truck carrying a broken bag of cement with no tail gate"
  },
  {
    "url": "https://photos.peterlyons.com/2009/2009-04-09-01425GFRKR6JG819BX1WRJRY1X.2048.jpg",
    "caption": "Vancouver"
  },
  {
    "url": "https://photos.peterlyons.com/2009/2009-04-09-01425GG0DRQFBFXT0VSY38XTG3.2048.jpg",
    "caption": "Vancouver"
  },
  {
    "url": "https://photos.peterlyons.com/2009/2009-04-09-01425GMD1R79NZHS5S657599MR.2048.jpg",
    "caption": "Gull near Coal Harbor"
  },
  {
    "url": "https://photos.peterlyons.com/2009/2009-04-09-01425GPY3GW0YMD4K2SBKS07TQ.2048.jpg",
    "caption": "Sea plane taking off"
  },
  {
    "url": "https://photos.peterlyons.com/2009/2009-04-09-01425GWTJRE5WDFDCQZY2K1Q5N.2048.jpg",
    "caption": "010_vancouver_reflection"
  },
  {
    "url": "https://photos.peterlyons.com/2009/2009-04-09-01425GX2CRTY5PHQZNPAT1N0ZQ.2048.jpg",
    "caption": "011_vancouver_reflection"
  },
  {
    "url": "https://photos.peterlyons.com/2009/2009-04-09-01425M18EGH4GN9VXWFQGFMDXW.2048.jpg",
    "caption": "Andrew checking out a Carla Bley record with Steve Slagle"
  },
  {
    "url": "https://photos.peterlyons.com/2009/2009-04-09-01425N5DNR9K16R397CFND32RQ.2048.jpg",
    "caption": "013_vancouver_scientology"
  },
  {
    "url": "https://photos.peterlyons.com/2009/2009-04-09-01425NXAAG9045QMD9WM6PX1E6.2048.jpg",
    "caption": "014_vancouver_call_your_mom"
  },
  {
    "url": "https://photos.peterlyons.com/2009/2009-04-09-01425Q2DTGPF4J4Q72M0CJK3X2.2048.jpg",
    "caption": "Apartment building with some murals and words on the balconies"
  },
  {
    "url": "https://photos.peterlyons.com/2009/2009-04-09-0142616380SK76HFGFME0SHEQB.2048.jpg",
    "caption": "Coal Harbor and the Vancouver skyline"
  },
  {
    "url": "https://photos.peterlyons.com/2009/2009-04-09-0142616A2RF609C9FAXSVEBZN6.2048.jpg",
    "caption": "017_vancouver_coal_harbor"
  },
  {
    "url": "https://photos.peterlyons.com/2009/2009-04-09-014262599GZTT4M3TAC37JA45J.2048.jpg",
    "caption": "Vancouver Theatre Sports Leage"
  },
  {
    "url": "https://photos.peterlyons.com/2009/2009-04-09-014265PP6GQ0YKSES63SC8S4F8.2048.jpg",
    "caption": "At the Sandbar restaurant"
  },
  {
    "url": "https://photos.peterlyons.com/2009/2009-04-09-014269TC28ZRSQK527P0E9QMZ3.2048.jpg",
    "caption": "A big rube goldberg art piece in front of a cement company"
  },
  {
    "url": "https://photos.peterlyons.com/2009/2009-04-09-014269TQS8BRSVR4Y146RSDYBN.2048.jpg",
    "caption": "A big rube goldberg art piece in front of a cement company"
  },
  {
    "url": "https://photos.peterlyons.com/2009/2009-04-10-0142816SV0JPVVPNYSE4A84J94.2048.jpg",
    "caption": "Vietnamese food from Le Don"
  },
  {
    "url": "https://photos.peterlyons.com/2009/2009-04-10-014284NEVG0Q522QZR07F0AJ3R.2048.jpg",
    "caption": "Cypress Provincial Park view point"
  },
  {
    "url": "https://photos.peterlyons.com/2009/2009-04-10-01428DQPY81B3V306DGMKJHMZY.2048.jpg",
    "caption": "Varley Trail"
  },
  {
    "url": "https://photos.peterlyons.com/2009/2009-04-10-01428DWEA0F146SR1C4F50V47M.2048.jpg",
    "caption": "Varley Trail"
  },
  {
    "url": "https://photos.peterlyons.com/2009/2009-04-10-01428ESTQRPVFJTW6381JXCKK8.2048.jpg",
    "caption": "Varley Trail"
  },
  {
    "url": "https://photos.peterlyons.com/2009/2009-04-10-01428ET2HR4YNRNQ1FM9PWT9Q9.2048.jpg",
    "caption": "Varley Trail"
  },
  {
    "url": "https://photos.peterlyons.com/2009/2009-04-10-01428G494G57CJ9GS59Z254MX5.2048.jpg",
    "caption": "Varley Trail"
  },
  {
    "url": "https://photos.peterlyons.com/2009/2009-04-10-01428NN68RN6GHHXWDT9940RRX.2048.jpg",
    "caption": "Mirror portrait in the Subeez bathroom"
  },
  {
    "url": "https://photos.peterlyons.com/2009/2009-04-11-0142A7JQBRSQNHA1Z2MJGEE63D.2048.jpg",
    "caption": "Another classic pick up truck improperly secured load! I think it's probably Cap'n Crunch."
  }
]
